plugins/starzai_memu/__init__.py
plugins/starzai_memu/config.py
nonebot_plugin_starzai_memu-0.1.3.dist-info/METADATA
nonebot_plugin_starzai_memu-0.1.3.dist-info/WHEEL
nonebot_plugin_starzai_memu-0.1.3.dist-info/top_level.txt
nonebot_plugin_starzai_memu-0.1.3.dist-info/RECORD
