Metadata-Version: 2.1
Name: nonebot-plugin-starzai-memu
Version: 0.1.3
Summary: 星崽BOt-菜单
Requires-Python: <4.0,>=3.8
Requires-Dist: nonebot2
